pydeface/__init__.py
pydeface/__main__.py
pydeface/utils.py
pydeface/data/facemask.nii.gz
pydeface/data/mean_reg2mean.nii.gz
pydeface-2.0.2.dist-info/LICENSE.txt
pydeface-2.0.2.dist-info/METADATA
pydeface-2.0.2.dist-info/WHEEL
pydeface-2.0.2.dist-info/entry_points.txt
pydeface-2.0.2.dist-info/top_level.txt
pydeface-2.0.2.dist-info/RECORD
