Metadata-Version: 2.1
Name: pydeface
Version: 2.0.2
Summary: A script to remove facial structure from MRI images.
Home-page: http://poldracklab.org
Download-URL: https://github.com/poldracklab/pydeface/archive/2.0.2.tar.gz
Maintainer: Russ Poldrack
Maintainer-email: poldrack@stanford.edu
License: MIT
Classifier: Intended Audience :: Science/Research
Classifier: Programming Language :: Python :: 3.7
Classifier: License :: OSI Approved :: MIT License
Classifier: Operating System :: POSIX
Classifier: Operating System :: Unix
Classifier: Operating System :: MacOS
License-File: LICENSE.txt
Requires-Dist: numpy
Requires-Dist: nibabel
Requires-Dist: nipype
Requires-Dist: setuptools
